README.md
setup.cfg
setup.py
prometheus_jenkins_exporter/__init__.py
prometheus_jenkins_exporter/exporter.py
prometheus_jenkins_exporter.egg-info/PKG-INFO
prometheus_jenkins_exporter.egg-info/SOURCES.txt
prometheus_jenkins_exporter.egg-info/dependency_links.txt
prometheus_jenkins_exporter.egg-info/entry_points.txt
prometheus_jenkins_exporter.egg-info/requires.txt
prometheus_jenkins_exporter.egg-info/top_level.txt