Metadata-Version: 1.2
Name: prometheus-jenkins-exporter
Version: 0.2.3
Summary: Prometheus exporter for Jenkins
Home-page: https://github.com/spreaker/prometheus-jenkins-exporter
Author: Marco Pracucci
Author-email: marco@pracucci.com
License: UNKNOWN
Download-URL: https://github.com/spreaker/prometheus-jenkins-exporter/archive/0.2.2.tar.gz
Keywords: prometheus,jenkins
Platform: UNKNOWN
Requires-Python: >=3
